overloading.py
overloading-0.4.0.dist-info/DESCRIPTION.rst
overloading-0.4.0.dist-info/METADATA
overloading-0.4.0.dist-info/metadata.json
overloading-0.4.0.dist-info/RECORD
overloading-0.4.0.dist-info/top_level.txt
overloading-0.4.0.dist-info/WHEEL
