Metadata-Version: 2.0
Name: overloading
Version: 0.4.0
Summary: Function overloading for Python 3
Home-page: https://github.com/bintoro/overloading.py
Author: Kalle Tuure
Author-email: kalle@goodtimes.fi
License: MIT
Platform: UNKNOWN
Classifier: Programming Language :: Python
Classifier: Programming Language :: Python :: 3
Classifier: Programming Language :: Python :: 3 :: Only
